ada/__init__.py
ada/myfunctions.py
ada_utils/__init__.py
ada_utils/myfunctions.py
ada_utils-0.2.0.dist-info/METADATA
ada_utils-0.2.0.dist-info/WHEEL
ada_utils-0.2.0.dist-info/top_level.txt
ada_utils-0.2.0.dist-info/RECORD
