Metadata-Version: 2.1
Name: ada-utils
Version: 0.2.0
Summary: General purpose Python library for use of Migros Advanced Data Analytics Team
Author: M.O.
License: MIT
Requires-Dist: numpy (==1.23.5)
